[
    {
        "cid": "0x0c1f3e9d4b7a8210f6bc68b27c1cd061d45aef87fd5a4986f85ae39d8a57b0d7",
        "dateAccessed": 1647826289000,
        "dateModified": 1647830000000,
        "dateUploaded": 1647831000000,
        "description": "Document for project presentation",
        "extension": "png",
        "isArchived": false,
        "isFavourite": false,
        "name": "Project Presentation",
        "owner": "0x8626f6940E2eb28930eFb4CeF49B2d1F2C9C1199",
        "size": 25500,
        "tag": 1,
        "isShared": true,
        "isDeleted": false
    },
    {
        "cid": "0x3f8df0b1eddb398d176fd5d6ef2f9d52d45b1d79dca4320d4d77331dc2c24eb3",
        "dateAccessed": 1647826289000,
        "dateModified": 1647831000000,
        "dateUploaded": 1647832000000,
        "description": "Financial report for Q1",
        "extension": "png",
        "isArchived": false,
        "isFavourite": true,
        "name": "Financial Report Q1",
        "owner": "0x1234567890ABCDEF",
        "size": 10200000,
        "tag": 4,
        "isShared": false,
        "isDeleted": true
    },
    {
        "cid": "0x2b99cc97e5b0f8b3f7c2c6ddcdd0e93c0fe60aef849f0786bbdddc860dc34f9c",
        "dateAccessed": 1647826289000,
        "dateModified": 1647832000000,
        "dateUploaded": 1647833000000,
        "description": "Healthcare data analysis",
        "extension": "png",
        "isArchived": false,
        "isFavourite": true,
        "name": "Healthcare Data Analysis",
        "owner": "0xA1B2C3D4E5F6",
        "size": 5600,
        "tag": 2,
        "isShared": false,
        "isDeleted": true
    },
    {
        "cid": "0x6b2b3f6d47c728a3d4f57d5fe2c5d59700b19025e2790e290c2adef46e4a61b1",
        "dateAccessed": 1647826289000,
        "dateModified": 1647833000000,
        "dateUploaded": 1647834000000,
        "description": "Marketing campaign analytics",
        "extension": "png",
        "isArchived": false,
        "isFavourite": true,
        "name": "Marketing Campaign Analytics",
        "owner": "0x1234567890ABCDEF",
        "size": 100300,
        "tag": 3,
        "isShared": true,
        "isDeleted": false
    },
    {
        "cid": "0x80fc87b195a54d3d52b03fb105af31737d121aaac3d2eef1d1ff3b11d3d1797d",
        "dateAccessed": 1647826289000,
        "dateModified": 1647834000000,
        "dateUploaded": 1647835000000,
        "description": "Design mockup for new app",
        "extension": "png",
        "isArchived": false,
        "isFavourite": false,
        "name": "Design Mockup New App",
        "owner": "0xFEDCBA0987654321",
        "size": 50700000,
        "tag": 4,
        "isShared": false,
        "isDeleted": false
    },
    {
        "cid": "0xa1912b7313b2ccaf94f5c7a5310d9c1c05c6cd98bada5b9c20c38f79c1a22a78",
        "dateAccessed": 1647826289000,
        "dateModified": 1647835000000,
        "dateUploaded": 1647836000000,
        "description": "Quarterly sales data",
        "extension": "png",
        "isArchived": false,
        "isFavourite": true,
        "name": "Quarterly Sales Data",
        "owner": "0xA1B2C3D4E5F6",
        "size": 1800000,
        "tag": 3,
        "isShared": false,
        "isDeleted": false
    },
    {
        "cid": "0x18aee8d1cb7aa0c5ff6e034a5b7f5a92e012f749b2f1161bf7a3313a30bb5a1a",
        "dateAccessed": 1647826289000,
        "dateModified": 1647836000000,
        "dateUploaded": 1647837000000,
        "description": "Research findings on consumer behavior",
        "extension": "png",
        "isArchived": false,
        "isFavourite": false,
        "name": "Consumer Behavior Research",
        "owner": "0x8626f6940E2eb28930eFb4CeF49B2d1F2C9C1199",
        "size": 35200000,
        "tag": 5,
        "isShared": false,
        "isDeleted": false
    },
    {
        "cid": "0x43194d7f21ef1f312e9d24c6565cb28f7fcac51e778477d91691a87e8eb083a7",
        "dateAccessed": 1647826289000,
        "dateModified": 1647837000000,
        "dateUploaded": 1647838000000,
        "description": "Proposal for new project",
        "extension": "png",
        "isArchived": false,
        "isFavourite": true,
        "name": "New Project Proposal",
        "owner": "0xFEDCBA0987654321",
        "size": 12600000,
        "tag": 1,
        "isShared": false,
        "isDeleted": false
    },
    {
        "cid": "0x703aa7d80c23cd11f18388b3a892ee285cb89ed0de348aa3e7c00e0a05d17bb4","dateAccessed": 1647826289000,
        "dateModified": 1647838000000,
        "dateUploaded": 1647839000000,
        "description": "Product launch plan",
        "extension": "png",
        "isArchived": false,
        "isFavourite": true,
        "name": "Product Launch Plan",
        "owner": "0x1234567890ABCDEF",
        "size": 2300000,
        "tag": 2,
        "isShared": true,
        "isDeleted": false
    },
    {
        "cid": "0x3b61f831152e5e8695c4bb0f9ebd4fcb6afdb06a9b6e0fd087bc193f785a18b2",
        "dateAccessed": 1647826289000,
        "dateModified": 1647839000000,
        "dateUploaded": 1647840000000,
        "description": "User interface design for mobile app",
        "extension": "png",
        "isArchived": false,
        "isFavourite": false,
        "name": "Mobile App UI Design",
        "owner": "0x1234567890ABCDEF",
        "size": 4100000,
        "tag": 4,
        "isShared": false,
        "isDeleted": false
    },
    {
        "cid": "0xc12fe6d3ed438d61c4a17a36f882bfc4b26b19d9e184c7d5de78633dd9d82694",
        "dateAccessed": 1647826289000,
        "dateModified": 1647840000000,
        "dateUploaded": 1647841000000,
        "description": "Monthly sales report",
        "extension": "png",
        "isArchived": false,
        "isFavourite": true,
        "name": "Monthly Sales Report",
        "owner": "0xA1B2C3D4E5F6",
        "size": 8900000,
        "tag": 3,
        "isShared": false,
        "isDeleted": false
    },
    {
        "cid": "0x6011e72f60b82b2f1d9a26ff14a33d9d47ed040f98642cc7d36bb5d46ed1a09a",
        "dateAccessed": 1647826289000,
        "dateModified": 1647841000000,
        "dateUploaded": 1647842000000,
        "description": "Research paper on market trends",
        "extension": "png",
        "isArchived": false,
        "isFavourite": true,
        "name": "Market Trends Research",
        "owner": "0x8626f6940E2eb28930eFb4CeF49B2d1F2C9C1199",
        "size": 3700000,
        "tag": 5,
        "isShared": false,
        "isDeleted": false
    }
]